Blammer/__init__.py
Gdader-0.0.3.dist-info/METADATA
Gdader-0.0.3.dist-info/WHEEL
Gdader-0.0.3.dist-info/top_level.txt
Gdader-0.0.3.dist-info/RECORD
