Metadata-Version: 2.1
Name: Gdader
Version: 0.0.3
Summary: Must have a helper with you
Author: Coder100
Author-email: jacobhason86@gmail.com
